uncommon/__init__.py
uncommon/__main__.py
uncommon/uncommon.py
uncommon/data/words.txt
uncommon-0.0.4.dist-info/LICENSE.md
uncommon-0.0.4.dist-info/METADATA
uncommon-0.0.4.dist-info/WHEEL
uncommon-0.0.4.dist-info/entry_points.txt
uncommon-0.0.4.dist-info/top_level.txt
uncommon-0.0.4.dist-info/RECORD
