Metadata-Version: 2.1
Name: uncommon
Version: 0.0.4
Summary: A Python package of uncommon words created using carcass
Home-page: https://github.com/MSAdministrator/uncommon
Author: MSAdministrator
Author-email: 
License: MIT
Keywords: carcass
Platform: UNKNOWN
Requires-Python: >=2.6, !=3.0.*, !=3.1.*, !=3.2.*, <4
Requires-Dist: fire
